pyhrmc/__init__.py
pyhrmc/core/__init__.py
pyhrmc/core/hrmc.py
pyhrmc/core/interpolator.py
pyhrmc/core/rmc.py
pyhrmc/core/rmc_rdf.py
pyhrmc/core/slab.py
pyhrmc/transformers/__init__.py
pyhrmc/transformers/atom_hop.py
pyhrmc/transformers/base.py
pyhrmc/validators/__init__.py
pyhrmc/validators/base.py
pyhrmc/validators/coordination.py
pyhrmc/validators/distances_coordination.py
pyhrmc/validators/site_distance.py
pyhrmc/validators/slab_thickness.py
pyhrmc/validators/target_density.py
pyhrmc_dev-0.0.0.dist-info/LICENSE.md
pyhrmc_dev-0.0.0.dist-info/METADATA
pyhrmc_dev-0.0.0.dist-info/WHEEL
pyhrmc_dev-0.0.0.dist-info/top_level.txt
pyhrmc_dev-0.0.0.dist-info/RECORD
